OViewPy/__init__.py
OViewPy/da.py
OViewPy/layer.py
OViewPy/oviewlayer.py
OViewPy/server.py
OViewPy/varstruct.py
OViewPy-1.2.1.dist-info/METADATA
OViewPy-1.2.1.dist-info/WHEEL
OViewPy-1.2.1.dist-info/license.txt
OViewPy-1.2.1.dist-info/top_level.txt
OViewPy-1.2.1.dist-info/RECORD
