Metadata-Version: 2.1
Name: OViewPy
Version: 1.2.1
Summary: PilotGaea O'View Map Server API for Python
Home-page: https://github.com/PilotGaea/OViewPy
Author: louis.li
Author-email: louis.li@pilotgaea.com.tw
License: UNKNOWN
Platform: UNKNOWN
Classifier: Programming Language :: Python :: 3
Classifier: License :: OSI Approved :: MIT License
Classifier: Topic :: Scientific/Engineering :: GIS
Requires-Python: >=3.6
Requires-Dist: requests
Requires-Dist: numpy
Requires-Dist: opencv-python
Requires-Dist: progress
Requires-Dist: shapely
Requires-Dist: PyShp
Requires-Dist: rasterio
Requires-Dist: matplotlib
Requires-Dist: sridentify
Requires-Dist: geojsoncontour
